{
    "16700": "Uushaa!!",
    "17450": "Kecepatan, Kekuatan, Stamina",
    "18867": "Kecepatan, Kekuatan, Stamina",
    "20500": "Kecepatan, Kekuatan, Stamina",
    "22150": "Tekad, Keilmuan",
    "23767": "Kecepatan, Kekuatan, Stamina",
    "25383": "Kecepatan, Kekuatan, Stamina",
    "27000": "Kecepatan, Kekuatan, Stamina",
    "28517": "Tekad, Keilmuan",
    "30250": "Hei! Kalau mau cepat, kerja keras dong",
    "33517": "Boo… Bukankah istirahat juga penting? (Jadi?...)",
    "36900": "Mau minggu santai? atau minggu biasa (berkeringat)?",
    "39583": "Minggu yang normal (penuh keringat) saja deh!",
    "41183": "Ayo- Mantul! ×4",
    "50100": "Tidak apa-apa jadi diri sendiri! (Bon x3)",
    "53433": "Kini rasakan bebasnya tubuhmu (Bon×3)",
    "56750": "Bukankah hebat → Menjadi diri kita sendiri?",
    "59267": "Lalala Kanan & Kiri",
    "61417": "dan BERLARI untuk LARI (Enjoy♪)",
    "63267": "Mari jadi diri kita sendiri!",
    "66783": "Lupakan semuanya dan「 Rasakan sekarang 」(Bon×3)",
    "70100": "Bukankah terbaik → Menjadi diri sendiri?",
    "72600": "Lalala Kanan & Kiri",
    "74617": "dan BERLARI untuk BERLARI",
    "79867": "Kecepatan, Kekuatan, Stamina",
    "81467": "Kecepatan, Kekuatan, Stamina",
    "83050": "Kecepatan, Kekuatan, Stamina",
    "84700": "Tekad, Keilmuan",
    "86267": "Kecepatan! Kekuatan! Daya tahan!",
    "87800": "Kecepatan! Kekuatan! Daya tahan!",
    "89350": "Kecepatan! Kekuatan! Daya tahan!",
    "90917": "Tekad, Keilmuan",
    "92467": "Kecepatan!! Kekuatan!! Daya tahan!!",
    "93933": "Kecepatan!! Kekuatan!! Daya tahan!!",
    "95433": "Kecepatan!! Kekuatan!! Daya tahan!!",
    "96933": "Tekad, Keilmuan",
    "98417": "Kecepatan!! Kekuatan!! Daya tahan!!",
    "99933": "Kecepatan!! Kekuatan!! Daya tahan!!",
    "101450": "Kecepatan!! Kekuatan!! Daya tahan!!",
    "102933": "Tekad, Keilmuan",
    "104500": "Kecepatan!! Kekuatan!! Daya tahan!!",
    "105950": "Kecepatan!! Kekuatan!! Daya tahan!!",
    "107450": "Kecepatan!! Kekuatan!! Daya tahan!!",
    "108917": "Tekad, Keilmuan",
    "110433": "Kecepatan!! Kekuatan!! Daya tahan!!",
    "111933": "Kecepatan!! Kekuatan!! Daya tahan!!",
    "113417": "Kecepatan!! Kekuatan!! Daya tahan!!",
    "114933": "Tekad, Keilmuan!!!!"
}
